zxcvbn/__init__.py
zxcvbn/adjacency_graphs.py
zxcvbn/feedback.py
zxcvbn/frequency_lists.py
zxcvbn/matching.py
zxcvbn/scoring.py
zxcvbn/time_estimates.py
zxcvbn_python-4.4.19.dist-info/DESCRIPTION.rst
zxcvbn_python-4.4.19.dist-info/METADATA
zxcvbn_python-4.4.19.dist-info/RECORD
zxcvbn_python-4.4.19.dist-info/WHEEL
zxcvbn_python-4.4.19.dist-info/metadata.json
zxcvbn_python-4.4.19.dist-info/top_level.txt
